eventsourcing_dynamodb/__init__.py
eventsourcing_dynamodb/factory.py
eventsourcing_dynamodb/models.py
eventsourcing_dynamodb/py.typed
eventsourcing_dynamodb/recorders.py
eventsourcing_dynamodb-0.1.0.dist-info/LICENSE
eventsourcing_dynamodb-0.1.0.dist-info/METADATA
eventsourcing_dynamodb-0.1.0.dist-info/WHEEL
eventsourcing_dynamodb-0.1.0.dist-info/RECORD
