Metadata-Version: 2.1
Name: eventsourcing-dynamodb
Version: 0.1.0
Summary: Python package for eventsourcing with DynamoDB
Home-page: https://github.com/pyeventsourcing/eventsourcing-dynamodb
License: BSD 3-Clause
Author: John Bywater
Author-email: john.bywater@appropriatesoftware.net
Requires-Python: >=3.10,<4.0
Classifier: Development Status :: 4 - Beta
Classifier: License :: OSI Approved :: BSD License
Classifier: License :: Other/Proprietary License
Classifier: Programming Language :: Python
Classifier: Programming Language :: Python :: 3
Classifier: Programming Language :: Python :: 3.10
Classifier: Programming Language :: Python :: 3.11
Classifier: Programming Language :: Python :: 3.12
Classifier: Programming Language :: Python :: 3.13
Requires-Dist: boto3 (>=1.36,<2.0.0)
Requires-Dist: eventsourcing (>=9.3,<9.4)
Project-URL: Repository, https://github.com/pyeventsourcing/eventsourcing-dynamodb
